Kyoukai-2.2.1.post1.dist-info/DESCRIPTION.rst
Kyoukai-2.2.1.post1.dist-info/METADATA
Kyoukai-2.2.1.post1.dist-info/RECORD
Kyoukai-2.2.1.post1.dist-info/WHEEL
Kyoukai-2.2.1.post1.dist-info/metadata.json
Kyoukai-2.2.1.post1.dist-info/top_level.txt
kyoukai/__init__.py
kyoukai/app.py
kyoukai/asphalt.py
kyoukai/blueprint.py
kyoukai/route.py
kyoukai/routegroup.py
kyoukai/testing.py
kyoukai/util.py
kyoukai/wsgi.py
kyoukai/backends/__init__.py
kyoukai/backends/gunicorn.py
kyoukai/backends/http2.py
kyoukai/backends/httptools_.py
kyoukai/backends/uwsgi.py
